{
    "die-1-septembris": {
        "la": "Die 1 septembris",
        "en": "On 1 September",
        "pl": "Dnia 1 września"
    },
    "die-2-septembris": {
        "la": "Die 2 septembris",
        "en": "On 2 September",
        "pl": "Dnia 2 września"
    },
    "die-3-septembris": {
        "la": "Die 3 septembris",
        "en": "On 3 September",
        "pl": "Dnia 3 września"
    },
    "die-4-septembris": {
        "la": "Die 4 septembris",
        "en": "On 4 September",
        "pl": "Dnia 4 września"
    },
    "die-5-septembris": {
        "la": "Die 5 septembris",
        "en": "On 5 September",
        "pl": "Dnia 5 września"
    },
    "die-6-septembris": {
        "la": "Die 6 septembris",
        "en": "On 6 September",
        "pl": "Dnia 6 września"
    },
    "die-7-septembris": {
        "la": "Die 7 septembris",
        "en": "On 7 September",
        "pl": "Dnia 7 września"
    },
    "die-8-septembris": {
        "la": "Die 8 septembris",
        "en": "On 8 September",
        "pl": "Dnia 8 września"
    },
    "die-9-septembris": {
        "la": "Die 9 septembris",
        "en": "On 9 September",
        "pl": "Dnia 9 września"
    },
    "die-10-septembris": {
        "la": "Die 10 septembris",
        "en": "On 10 September",
        "pl": "Dnia 10 września"
    },
    "die-11-septembris": {
        "la": "Die 11 septembris",
        "en": "On 11 September",
        "pl": "Dnia 11 września"
    },
    "die-12-septembris": {
        "la": "Die 12 septembris",
        "en": "On 12 September",
        "pl": "Dnia 12 września"
    },
    "die-13-septembris": {
        "la": "Die 13 septembris",
        "en": "On 13 September",
        "pl": "Dnia 13 września"
    },
    "die-14-septembris": {
        "la": "Die 14 septembris",
        "en": "On 14 September",
        "pl": "Dnia 14 września"
    },
    "die-15-septembris": {
        "la": "Die 15 septembris",
        "en": "On 15 September",
        "pl": "Dnia 15 września"
    },
    "die-16-septembris": {
        "la": "Die 16 septembris",
        "en": "On 16 September",
        "pl": "Dnia 16 września"
    },
    "die-17-septembris": {
        "la": "Die 17 septembris",
        "en": "On 17 September",
        "pl": "Dnia 17 września"
    },
    "die-18-septembris": {
        "la": "Die 18 septembris",
        "en": "On 18 September",
        "pl": "Dnia 18 września"
    },
    "die-19-septembris": {
        "la": "Die 19 septembris",
        "en": "On 19 September",
        "pl": "Dnia 19 września"
    },
    "die-20-septembris": {
        "la": "Die 20 septembris",
        "en": "On 20 September",
        "pl": "Dnia 20 września"
    },
    "die-21-septembris": {
        "la": "Die 21 septembris",
        "en": "On 21 September",
        "pl": "Dnia 21 września"
    },
    "die-22-septembris": {
        "la": "Die 22 septembris",
        "en": "On 22 September",
        "pl": "Dnia 22 września"
    },
    "die-23-septembris": {
        "la": "Die 23 septembris",
        "en": "On 23 September",
        "pl": "Dnia 23 września"
    },
    "die-24-septembris": {
        "la": "Die 24 septembris",
        "en": "On 24 September",
        "pl": "Dnia 24 września"
    },
    "die-25-septembris": {
        "la": "Die 25 septembris",
        "en": "On 25 September",
        "pl": "Dnia 25 września"
    },
    "die-26-septembris": {
        "la": "Die 26 septembris",
        "en": "On 26 September",
        "pl": "Dnia 26 września"
    },
    "die-27-septembris": {
        "la": "Die 27 septembris",
        "en": "On 27 September",
        "pl": "Dnia 27 września"
    },
    "die-28-septembris": {
        "la": "Die 28 septembris",
        "en": "On 28 September",
        "pl": "Dnia 28 września"
    },
    "die-29-septembris": {
        "la": "Die 29 septembris",
        "en": "On 29 September",
        "pl": "Dnia 29 września"
    },
    "die-30-septembris": {
        "la": "Die 30 septembris",
        "en": "On 30 September",
        "pl": "Dnia 30 września"
    }
}
